event_judge/__init__.py
event_judge-0.1.dist-info/LICENSE
event_judge-0.1.dist-info/METADATA
event_judge-0.1.dist-info/WHEEL
event_judge-0.1.dist-info/top_level.txt
event_judge-0.1.dist-info/RECORD
