Metadata-Version: 2.1
Name: event-judge
Version: 0.1
Summary: Simplifying judging for all events
Home-page: https://github.com/isohack/event-judge
Author: Shashank Sharma
Author-email: shashank.sharma98@gmail.com
License: MIT
Platform: UNKNOWN
